swh/web/client/__init__.py
swh/web/client/cli.py
swh/web/client/client.py
swh/web/client/py.typed
swh/web/client/tests/__init__.py
swh/web/client/tests/api_data.py
swh/web/client/tests/api_data_static.py
swh/web/client/tests/conftest.py
swh/web/client/tests/gen-api-data.sh
swh/web/client/tests/test_cli.py
swh/web/client/tests/test_web_api_client.py
swh_web_client-0.9.2.dist-info/licenses/AUTHORS
swh_web_client-0.9.2.dist-info/licenses/LICENSE
swh_web_client-0.9.2.dist-info/METADATA
swh_web_client-0.9.2.dist-info/WHEEL
swh_web_client-0.9.2.dist-info/entry_points.txt
swh_web_client-0.9.2.dist-info/top_level.txt
swh_web_client-0.9.2.dist-info/RECORD
